{
    "scientificName": "Osbeckia octandra DC.",
    "synonyms": [
        "Asterostoma octandra Blume",
        "Melastoma octandrum L.",
        "Osbeckia polycephala Naudin",
        "Osbeckia simsii DC."
    ],
    "familyName": "MELASTOMATACEAE",
    "englishNames": [],
    "sinhalaName": "Heen bovitiya (හීන් බෝවිටියා)",
    "description": "මීටර් 2ක් පමණ උසට වැඩෙන, හොඳින් අතු බෙදුණු කුඩා පඳුරු ශාකයකි. පත්‍ර 1.5-6 x 0.5-2 සෙ.මී. ප්‍රමාණයෙන් යුක්ත වන අතර පත්‍ර වෘන්තය (petiole) මි.මී. 1-5ක් දිගය. මල් ස්වල්පයක් හෝ 10ක් දක්වා වූ ලිහිල් පොකුරු ලෙස හටගනී; හයිපන්තියම (hypanthium) මි.මී. 3-6ක් පළලය; පෙති මි.මී. 15-19ක් දිග වන අතර රෝස, ලා දම් හෝ තද දම් පැහැයෙන් යුක්ත වේ. ඵලය වියළි කරලක් (capsule) ලෙස පවතින අතර එය නොවැටී පවතින හයිපන්තියම තුළ පිහිටයි; බීජ රාශියක් ඇත.",
    "treatments": [
        {
            "treatment": "Diabetes mellitus",
            "sinhala": "දියවැඩියාව",
            "procedure": ""
        },
        {
            "treatment": "Haemorrhoids",
            "sinhala": "අර්ශස්",
            "procedure": ""
        },
        {
            "treatment": "Hepatitis",
            "sinhala": "හෙපටයිටිස් (අක්මා ප්‍රදාහය)",
            "procedure": ""
        },
        {
            "treatment": "Ascites",
            "sinhala": "මහෝදරය (උදරයේ දියර පිරීම)",
            "procedure": ""
        },
        {
            "treatment": "Liver disorders",
            "sinhala": "අක්මාවේ ආබාධ",
            "procedure": ""
        },
        {
            "treatment": "Jaundice",
            "sinhala": "සංග්‍රාහක පණ්ඩුව / කහ උණ (කාමලාව)",
            "procedure": ""
        },
        {
            "treatment": "Hyperlipidaemia",
            "sinhala": "රුධිරයේ මේදය අධික වීම",
            "procedure": ""
        }
    ],
    "partsUsed": [
        "Leaves",
        "Root",
        "Bark"
    ],
    "images": [
        {
            "image_id": "433",
            "caption": "Habit of the species",
            "url": "http://www.instituteofayurveda.org/plants/images/plants/00814/plant00814-00433.jpg"
        },
        {
            "image_id": "434",
            "caption": "Flower",
            "url": "http://www.instituteofayurveda.org/plants/images/plants/00814/plant00814-00434.jpg"
        },
        {
            "image_id": "3740",
            "caption": "Flower (PMR)",
            "url": "http://www.instituteofayurveda.org/plants/images/plants/00814/plant00814-03740.jpg"
        },
        {
            "image_id": "3741",
            "caption": "Young Fruits (PMR)",
            "url": "http://www.instituteofayurveda.org/plants/images/plants/00814/plant00814-03741.jpg"
        },
        {
            "image_id": "3742",
            "caption": "Mature Fruits (PMR)",
            "url": "http://www.instituteofayurveda.org/plants/images/plants/00814/plant00814-03742.jpg"
        }
    ]
}