{
    "scientificName": "Bupleurum ramosissimum Wight & Arn.",
    "synonyms": [
        "Bupleurum falcatum var. ramosissimum (Wight & Arn.) Dalzell & A.Gibson",
        "Bupleurum mucronatum f. ramosissimum (Wight & Arn.) C.B.Clarke",
        "Bupleurum mucronatum f. typicum C.B.Clarke",
        "Bupleurum mucronatum Wight & Arn.",
        "Bupleurum nervosum Moon",
        "Bupleurum ramosissimum f. virgatum (Wight & Arn.) C.B.Clarke",
        "Bupleurum ramosissimum var. mucronatum Panigrahi & S.C.Mishra",
        "Bupleurum ramosissimum var. virgatum (Clarke) Panigrahi & S.C.Mishra",
        "Bupleurum ramosissimum var. wightii Bennet",
        "Bupleurum virgatum Wight & Arn.",
        "Bupleurum wightii Koso-Pol.",
        "Bupleurum wightii P.K.Mukh.",
        "Bupleurum wightii var. ramosissimum (Wight & Arn.) Chandrab."
    ],
    "familyName": "APIACEAE",
    "englishNames": [
        "Wild Castor"
    ],
    "sinhalaName": "Wal erandu (වල් එරඬු)",
    "description": "",
    "treatments": [
        {
            "treatment": "Herpes",
            "sinhala": "හර්පීස් (විසර්ප දද වර්ගයක්)",
            "procedure": "",
            "links": [],
            "mainCategory": {
                "english": "Dermatological & Skin Conditions",
                "sinhala": "චර්ම රෝග සහ සමේ ආබාධ"
            }
        },
        {
            "treatment": "Skin Disorders",
            "sinhala": "චර්ම රෝග (Skin Disorders)",
            "procedure": "",
            "links": [],
            "mainCategory": {
                "english": "Dermatological & Skin Conditions",
                "sinhala": "චර්ම රෝග සහ සමේ ආබාධ"
            }
        },
        {
            "treatment": "Gingivitis",
            "sinhala": "විදුරුමස් ප්‍රදාහය",
            "procedure": "",
            "links": [],
            "mainCategory": {
                "english": "Dental & Oral Cavity Diseases",
                "sinhala": "දන්ත සහ මුඛ කුහරය ආශ්‍රිත රෝග"
            }
        },
        {
            "treatment": "Rheumatism",
            "sinhala": "වාත රෝග (සන්ධි ප්‍රදාහය)",
            "procedure": "",
            "links": [],
            "mainCategory": {
                "english": "Musculoskeletal & Orthopedic Disorders",
                "sinhala": "අස්ථි, සන්ධි සහ මාංශ පේශි ආශ්‍රිත ආබාධ"
            }
        }
    ],
    "partsUsed": [
        "Roots",
        "Seeds",
        "Latex"
    ],
    "images": [
        {
            "image_id": "1669",
            "caption": "Habit",
            "url": "https://i.ibb.co/twMhSvXg/plant00093-01669.jpg"
        },
        {
            "image_id": "1670",
            "caption": "Twig",
            "url": "https://i.ibb.co/MkdB7SQr/plant00093-01670.jpg"
        },
        {
            "image_id": "1671",
            "caption": "Inflorescence",
            "url": "https://i.ibb.co/TqFMw344/plant00093-01671.jpg"
        }
    ]
}